dbteasy/__init__.py
dbteasy/main.py
dbteasy/tasks.py
dbteasy-0.2.6.dist-info/LICENSE
dbteasy-0.2.6.dist-info/METADATA
dbteasy-0.2.6.dist-info/WHEEL
dbteasy-0.2.6.dist-info/entry_points.txt
dbteasy-0.2.6.dist-info/top_level.txt
dbteasy-0.2.6.dist-info/RECORD
