Metadata-Version: 2.1
Name: dbteasy
Version: 0.2.6
Summary: A small package to simplify the use of dbt core
Home-page: https://github.com/ArthurMor4is/dbteasy
Author: Arthur Morais
Author-email: arthurfmmorais@gmail.com
Project-URL: Bug Tracker, https://github.com/ArthurMor4is/dbteasy/issues
Classifier: Programming Language :: Python :: 3
Classifier: License :: OSI Approved :: MIT License
Classifier: Operating System :: OS Independent
Requires-Python: >=3.9.13
License-File: LICENSE
Requires-Dist: invoke (==1.7.1)
